pyvibdmc/__init__.py
pyvibdmc/_version.py
pyvibdmc/pyvibdmc.py
pyvibdmc/analysis/__init__.py
pyvibdmc/analysis/analyze_wfn.py
pyvibdmc/analysis/extract_sim_info.py
pyvibdmc/analysis/plotter.py
pyvibdmc/analysis/rotator.py
pyvibdmc/sample_potentials/__init__.py
pyvibdmc/sample_potentials/FortPots/__init__.py
pyvibdmc/sample_potentials/FortPots/Partridge_Schwenke_H2O/Makefile
pyvibdmc/sample_potentials/FortPots/Partridge_Schwenke_H2O/README.md
pyvibdmc/sample_potentials/FortPots/Partridge_Schwenke_H2O/__init__.py
pyvibdmc/sample_potentials/FortPots/Partridge_Schwenke_H2O/calc_h2o_pot.f
pyvibdmc/sample_potentials/FortPots/Partridge_Schwenke_H2O/call_trl_h2o.py
pyvibdmc/sample_potentials/FortPots/Partridge_Schwenke_H2O/call_trl_h2o_gpu.py
pyvibdmc/sample_potentials/FortPots/Partridge_Schwenke_H2O/free_oh_wvfn.npy
pyvibdmc/sample_potentials/FortPots/Partridge_Schwenke_H2O/free_oh_wvfn_dense.npy
pyvibdmc/sample_potentials/FortPots/Partridge_Schwenke_H2O/h2o_potential.py
pyvibdmc/sample_potentials/FortPots/Partridge_Schwenke_H2O/h2o_trial_old.py
pyvibdmc/sample_potentials/FortPots/Partridge_Schwenke_H2O/h2opes_v2.f
pyvibdmc/sample_potentials/PythonPots/__init__.py
pyvibdmc/sample_potentials/PythonPots/harm_trial_wfn.py
pyvibdmc/sample_potentials/PythonPots/harmonicOscillator1D.py
pyvibdmc/sample_potentials/PythonPots/morse_osc_1d.py
pyvibdmc/sample_potentials/PythonPots/random.txt
pyvibdmc/sample_potentials/TensorflowPots/__init__.py
pyvibdmc/sample_potentials/TensorflowPots/call_sample_model.py
pyvibdmc/sample_potentials/TensorflowPots/sample_h4o2_nn.h5
pyvibdmc/sample_sim_data/tutorial_water_0_log.txt
pyvibdmc/sample_sim_data/tutorial_water_0_sim_info.hdf5
pyvibdmc/sample_sim_data/tutorial_water_1_log.txt
pyvibdmc/sample_sim_data/tutorial_water_1_sim_info.hdf5
pyvibdmc/sample_sim_data/tutorial_water_2_log.txt
pyvibdmc/sample_sim_data/tutorial_water_2_sim_info.hdf5
pyvibdmc/sample_sim_data/tutorial_water_3_log.txt
pyvibdmc/sample_sim_data/tutorial_water_3_sim_info.hdf5
pyvibdmc-1.3.9.dist-info/LICENSE
pyvibdmc-1.3.9.dist-info/METADATA
pyvibdmc-1.3.9.dist-info/WHEEL
pyvibdmc-1.3.9.dist-info/top_level.txt
pyvibdmc-1.3.9.dist-info/RECORD
