Metadata-Version: 2.1
Name: pyvibdmc
Version: 1.3.9
Summary: UNKNOWN
Home-page: http://pyvibdmc.readthedocs.io/
Author: Ryan DiRisio
Author-email: rjdiri@uw.edu
License: MIT
Platform: Linux
Platform: Mac OS-X
Platform: Unix
Platform: Windows
Requires-Python: >=3.5
